{"gianttv212.jpg": "gianttv", "85inchtv24.jpg": "85inchtv", "75inchtv157.jpg": "75inchtv", "gianttv75.jpg": "gianttv", "massivetv129.jpg": "massivetv", "gianttv102.jpg": "gianttv", "hugetv123.jpg": "hugetv", "75inchtv142.jpg": "75inchtv", "gianttv63.jpg": "gianttv", "massivetv160.jpg": "massivetv", "gianttv112.jpg": "gianttv", "gianttv183.jpg": "gianttv", "gianttv251.jpg": "gianttv", "gianttv8.jpg": "gianttv", "85inchtv57.jpg": "85inchtv", "massivetv157.jpg": "massivetv", "75inchtv250.jpg": "75inchtv", "85inchtv38.jpg": "85inchtv", "gianttv100.jpg": "gianttv", "hugetv255.jpg": "hugetv", "massivetv183.jpg": "massivetv", "gianttv2.jpg": "gianttv", "massivetv253.jpg": "massivetv", "75inchtv182.jpg": "75inchtv", "massivetv114.jpg": "massivetv", "massivetv74.jpg": "massivetv", "75inchtv242.jpg": "75inchtv", "85inchtv34.jpg": "85inchtv", "hugetv79.jpg": "hugetv", "75inchtv149.jpg": "75inchtv", "85inchtv39.jpg": "85inchtv", "massivetv58.jpg": "massivetv", "massivetv119.jpg": "massivetv", "75inchtv224.jpg": "75inchtv", "75inchtv94.jpg": "75inchtv", "hugetv167.jpg": "hugetv", "75inchtv239.jpg": "75inchtv", "75inchtv35.jpg": "75inchtv", "75inchtv111.jpg": "75inchtv", "massivetv148.jpg": "massivetv", "gianttv239.jpg": "gianttv", "massivetv104.jpg": "massivetv", "hugetv137.jpg": "hugetv", "75inchtv216.jpg": "75inchtv", "gianttv25.jpg": "gianttv", "hugetv163.jpg": "hugetv", "85inchtv5.jpg": "85inchtv", "massivetv175.jpg": "massivetv", "hugetv70.jpg": "hugetv", "hugetv208.jpg": "hugetv", "gianttv185.jpg": "gianttv", "hugetv36.jpg": "hugetv", "hugetv28.jpg": "hugetv", "hugetv21.jpg": "hugetv", "75inchtv10.jpg": "75inchtv", "massivetv17.jpg": "massivetv", "gianttv55.jpg": "gianttv", "75inchtv52.jpg": "75inchtv", "massivetv146.jpg": "massivetv", "massivetv3.jpg": "massivetv", "massivetv241.jpg": "massivetv", "75inchtv258.jpg": "75inchtv", "gianttv177.jpg": "gianttv", "gianttv172.jpg": "gianttv", "75inchtv132.jpg": "75inchtv", "hugetv95.jpg": "hugetv", "75inchtv148.jpg": "75inchtv", "75inchtv248.jpg": "75inchtv", "massivetv29.jpg": "massivetv", "massivetv186.jpg": "massivetv", "75inchtv44.jpg": "75inchtv", "gianttv120.jpg": "gianttv", "75inchtv184.jpg": "75inchtv", "massivetv144.jpg": "massivetv", "gianttv115.jpg": "gianttv", "massivetv46.jpg": "massivetv", "75inchtv110.jpg": "75inchtv", "hugetv215.jpg": "hugetv", "massivetv213.jpg": "massivetv", "gianttv244.jpg": "gianttv", "hugetv136.jpg": "hugetv", "gianttv144.jpg": "gianttv", "hugetv17.jpg": "hugetv", "gianttv118.jpg": "gianttv", "hugetv197.jpg": "hugetv", "hugetv194.jpg": "hugetv", "gianttv203.jpg": "gianttv", "hugetv257.jpg": "hugetv", "85inchtv72.jpg": "85inchtv", "75inchtv212.jpg": "75inchtv", "hugetv239.jpg": "hugetv", "gianttv73.jpg": "gianttv", "gianttv139.jpg": "gianttv", "hugetv23.jpg": "hugetv", "massivetv239.jpg": "massivetv", "75inchtv154.jpg": "75inchtv", "massivetv70.jpg": "massivetv", "75inchtv139.jpg": "75inchtv", "gianttv117.jpg": "gianttv", "75inchtv249.jpg": "75inchtv", "massivetv211.jpg": "massivetv", "hugetv212.jpg": "hugetv", "massivetv27.jpg": "massivetv", "75inchtv134.jpg": "75inchtv", "massivetv37.jpg": "massivetv", "massivetv35.jpg": "massivetv", "massivetv170.jpg": "massivetv", "hugetv141.jpg": "hugetv", "hugetv117.jpg": "hugetv", "75inchtv30.jpg": "75inchtv", "hugetv251.jpg": "hugetv", "75inchtv101.jpg": "75inchtv", "gianttv204.jpg": "gianttv", "hugetv116.jpg": "hugetv", "75inchtv98.jpg": "75inchtv", "gianttv57.jpg": "gianttv", "massivetv158.jpg": "massivetv", "hugetv34.jpg": "hugetv", "massivetv68.jpg": "massivetv", "hugetv19.jpg": "hugetv", "85inchtv9.jpg": "85inchtv", "85inchtv56.jpg": "85inchtv", "gianttv195.jpg": "gianttv", "75inchtv168.jpg": "75inchtv", "75inchtv243.jpg": "75inchtv", "hugetv5.jpg": "hugetv", "massivetv220.jpg": "massivetv", "hugetv55.jpg": "hugetv", "massivetv198.jpg": "massivetv", "hugetv196.jpg": "hugetv", "massivetv91.jpg": "massivetv", "gianttv37.jpg": "gianttv", "massivetv15.jpg": "massivetv", "85inchtv49.jpg": "85inchtv", "75inchtv190.jpg": "75inchtv", "hugetv82.jpg": "hugetv", "gianttv5.jpg": "gianttv", "75inchtv259.jpg": "75inchtv", "75inchtv126.jpg": "75inchtv", "75inchtv210.jpg": "75inchtv", "gianttv105.jpg": "gianttv", "gianttv110.jpg": "gianttv", "massivetv135.jpg": "massivetv", "gianttv60.jpg": "gianttv", "75inchtv38.jpg": "75inchtv", "gianttv103.jpg": "gianttv", "massivetv109.jpg": "massivetv", "gianttv188.jpg": "gianttv", "gianttv107.jpg": "gianttv", "hugetv191.jpg": "hugetv", "75inchtv195.jpg": "75inchtv", "gianttv169.jpg": "gianttv", "75inchtv15.jpg": "75inchtv", "massivetv212.jpg": "massivetv", "75inchtv47.jpg": "75inchtv", "hugetv8.jpg": "hugetv", "75inchtv124.jpg": "75inchtv", "gianttv140.jpg": "gianttv", "hugetv243.jpg": "hugetv", "hugetv156.jpg": "hugetv", "gianttv88.jpg": "gianttv", "massivetv217.jpg": "massivetv", "massivetv250.jpg": "massivetv", "75inchtv255.jpg": "75inchtv", "75inchtv217.jpg": "75inchtv", "massivetv128.jpg": "massivetv", "hugetv220.jpg": "hugetv", "gianttv86.jpg": "gianttv", "massivetv152.jpg": "massivetv", "85inchtv22.jpg": "85inchtv", "gianttv62.jpg": "gianttv", "hugetv118.jpg": "hugetv", "75inchtv244.jpg": "75inchtv", "massivetv122.jpg": "massivetv", "massivetv31.jpg": "massivetv", "hugetv71.jpg": "hugetv", "hugetv227.jpg": "hugetv", "hugetv159.jpg": "hugetv", "hugetv90.jpg": "hugetv", "hugetv228.jpg": "hugetv", "hugetv107.jpg": "hugetv", "75inchtv34.jpg": "75inchtv", "gianttv104.jpg": "gianttv", "gianttv187.jpg": "gianttv", "hugetv75.jpg": "hugetv", "massivetv192.jpg": "massivetv", "gianttv80.jpg": "gianttv", "75inchtv117.jpg": "75inchtv", "gianttv150.jpg": "gianttv", "massivetv26.jpg": "massivetv", "hugetv209.jpg": "hugetv", "75inchtv170.jpg": "75inchtv", "85inchtv62.jpg": "85inchtv", "75inchtv180.jpg": "75inchtv", "massivetv59.jpg": "massivetv", "massivetv169.jpg": "massivetv", "85inchtv47.jpg": "85inchtv", "75inchtv133.jpg": "75inchtv", "85inchtv21.jpg": "85inchtv", "massivetv165.jpg": "massivetv", "massivetv103.jpg": "massivetv", "85inchtv43.jpg": "85inchtv", "gianttv97.jpg": "gianttv", "gianttv218.jpg": "gianttv", "75inchtv160.jpg": "75inchtv", "massivetv112.jpg": "massivetv", "gianttv164.jpg": "gianttv", "75inchtv136.jpg": "75inchtv", "gianttv214.jpg": "gianttv", "hugetv86.jpg": "hugetv", "hugetv178.jpg": "hugetv", "gianttv92.jpg": "gianttv", "massivetv251.jpg": "massivetv", "75inchtv80.jpg": "75inchtv", "hugetv236.jpg": "hugetv", "75inchtv68.jpg": "75inchtv", "massivetv41.jpg": "massivetv", "massivetv60.jpg": "massivetv", "75inchtv204.jpg": "75inchtv", "gianttv96.jpg": "gianttv", "85inchtv74.jpg": "85inchtv", "hugetv225.jpg": "hugetv", "gianttv246.jpg": "gianttv", "85inchtv77.jpg": "85inchtv", "massivetv221.jpg": "massivetv", "gianttv222.jpg": "gianttv", "85inchtv41.jpg": "85inchtv", "massivetv243.jpg": "massivetv", "massivetv245.jpg": "massivetv", "75inchtv70.jpg": "75inchtv", "gianttv190.jpg": "gianttv", "75inchtv125.jpg": "75inchtv", "massivetv79.jpg": "massivetv", "hugetv237.jpg": "hugetv", "massivetv214.jpg": "massivetv", "gianttv76.jpg": "gianttv", "85inchtv65.jpg": "85inchtv", "gianttv173.jpg": "gianttv", "85inchtv27.jpg": "85inchtv", "massivetv159.jpg": "massivetv", "75inchtv58.jpg": "75inchtv", "massivetv256.jpg": "massivetv", "gianttv49.jpg": "gianttv", "hugetv258.jpg": "hugetv", "hugetv186.jpg": "hugetv", "85inchtv75.jpg": "85inchtv", "75inchtv93.jpg": "75inchtv", "gianttv217.jpg": "gianttv", "massivetv92.jpg": "massivetv", "75inchtv119.jpg": "75inchtv", "75inchtv12.jpg": "75inchtv", "hugetv76.jpg": "hugetv", "hugetv241.jpg": "hugetv", "gianttv182.jpg": "gianttv", "hugetv190.jpg": "hugetv", "massivetv154.jpg": "massivetv", "massivetv197.jpg": "massivetv", "75inchtv31.jpg": "75inchtv", "gianttv207.jpg": "gianttv", "massivetv38.jpg": "massivetv", "75inchtv120.jpg": "75inchtv", "gianttv223.jpg": "gianttv", "gianttv206.jpg": "gianttv", "85inchtv54.jpg": "85inchtv", "massivetv219.jpg": "massivetv", "gianttv194.jpg": "gianttv", "hugetv56.jpg": "hugetv", "massivetv149.jpg": "massivetv", "massivetv0.jpg": "massivetv", "massivetv76.jpg": "massivetv", "massivetv69.jpg": "massivetv", "massivetv111.jpg": "massivetv", "75inchtv175.jpg": "75inchtv", "75inchtv3.jpg": "75inchtv", "hugetv174.jpg": "hugetv", "hugetv32.jpg": "hugetv", "massivetv249.jpg": "massivetv", "75inchtv208.jpg": "75inchtv", "75inchtv97.jpg": "75inchtv", "massivetv201.jpg": "massivetv", "75inchtv39.jpg": "75inchtv", "gianttv125.jpg": "gianttv", "hugetv242.jpg": "hugetv", "hugetv140.jpg": "hugetv", "massivetv137.jpg": "massivetv", "gianttv230.jpg": "gianttv", "gianttv111.jpg": "gianttv", "75inchtv66.jpg": "75inchtv", "75inchtv115.jpg": "75inchtv", "massivetv133.jpg": "massivetv", "gianttv191.jpg": "gianttv", "gianttv54.jpg": "gianttv", "75inchtv14.jpg": "75inchtv", "hugetv51.jpg": "hugetv", "75inchtv107.jpg": "75inchtv", "massivetv84.jpg": "massivetv", "85inchtv20.jpg": "85inchtv", "75inchtv141.jpg": "75inchtv", "gianttv209.jpg": "gianttv", "hugetv33.jpg": "hugetv", "hugetv109.jpg": "hugetv", "gianttv33.jpg": "gianttv", "hugetv67.jpg": "hugetv", "massivetv184.jpg": "massivetv", "gianttv128.jpg": "gianttv", "massivetv1.jpg": "massivetv", "massivetv187.jpg": "massivetv", "gianttv233.jpg": "gianttv", "75inchtv237.jpg": "75inchtv", "gianttv245.jpg": "gianttv", "massivetv23.jpg": "massivetv", "massivetv105.jpg": "massivetv", "85inchtv55.jpg": "85inchtv", "hugetv230.jpg": "hugetv", "85inchtv58.jpg": "85inchtv", "75inchtv103.jpg": "75inchtv", "75inchtv53.jpg": "75inchtv", "75inchtv100.jpg": "75inchtv", "massivetv132.jpg": "massivetv", "massivetv116.jpg": "massivetv", "gianttv61.jpg": "gianttv", "75inchtv196.jpg": "75inchtv", "hugetv46.jpg": "hugetv", "hugetv247.jpg": "hugetv", "hugetv219.jpg": "hugetv", "85inchtv15.jpg": "85inchtv", "massivetv77.jpg": "massivetv", "hugetv198.jpg": "hugetv", "hugetv119.jpg": "hugetv", "massivetv71.jpg": "massivetv", "gianttv166.jpg": "gianttv", "massivetv130.jpg": "massivetv", "hugetv42.jpg": "hugetv", "75inchtv21.jpg": "75inchtv", "gianttv116.jpg": "gianttv", "massivetv138.jpg": "massivetv", "75inchtv48.jpg": "75inchtv", "massivetv97.jpg": "massivetv", "75inchtv122.jpg": "75inchtv", "massivetv13.jpg": "massivetv", "75inchtv145.jpg": "75inchtv", "75inchtv114.jpg": "75inchtv", "massivetv182.jpg": "massivetv", "gianttv162.jpg": "gianttv", "75inchtv231.jpg": "75inchtv", "75inchtv78.jpg": "75inchtv", "hugetv155.jpg": "hugetv", "85inchtv28.jpg": "85inchtv", "massivetv236.jpg": "massivetv", "gianttv90.jpg": "gianttv", "75inchtv96.jpg": "75inchtv", "gianttv250.jpg": "gianttv", "75inchtv251.jpg": "75inchtv", "gianttv189.jpg": "gianttv", "massivetv145.jpg": "massivetv", "75inchtv42.jpg": "75inchtv", "massivetv14.jpg": "massivetv", "gianttv227.jpg": "gianttv", "hugetv234.jpg": "hugetv", "85inchtv59.jpg": "85inchtv", "hugetv103.jpg": "hugetv", "hugetv259.jpg": "hugetv", "hugetv152.jpg": "hugetv", "hugetv154.jpg": "hugetv", "gianttv4.jpg": "gianttv", "hugetv85.jpg": "hugetv", "massivetv5.jpg": "massivetv", "gianttv232.jpg": "gianttv", "75inchtv85.jpg": "75inchtv", "massivetv115.jpg": "massivetv", "hugetv244.jpg": "hugetv", "massivetv227.jpg": "massivetv", "massivetv162.jpg": "massivetv", "hugetv115.jpg": "hugetv", "75inchtv221.jpg": "75inchtv", "massivetv172.jpg": "massivetv", "gianttv155.jpg": "gianttv", "gianttv224.jpg": "gianttv", "hugetv165.jpg": "hugetv", "massivetv136.jpg": "massivetv", "massivetv167.jpg": "massivetv", "gianttv253.jpg": "gianttv", "hugetv150.jpg": "hugetv", "gianttv153.jpg": "gianttv", "hugetv83.jpg": "hugetv", "hugetv238.jpg": "hugetv", "gianttv82.jpg": "gianttv", "massivetv215.jpg": "massivetv", "hugetv15.jpg": "hugetv", "massivetv33.jpg": "massivetv", "hugetv91.jpg": "hugetv", "hugetv173.jpg": "hugetv", "hugetv18.jpg": "hugetv", "hugetv135.jpg": "hugetv", "massivetv12.jpg": "massivetv", "massivetv7.jpg": "massivetv", "85inchtv19.jpg": "85inchtv", "75inchtv197.jpg": "75inchtv", "massivetv244.jpg": "massivetv", "hugetv229.jpg": "hugetv", "hugetv226.jpg": "hugetv", "75inchtv161.jpg": "75inchtv", "massivetv78.jpg": "massivetv", "75inchtv11.jpg": "75inchtv", "massivetv252.jpg": "massivetv", "75inchtv62.jpg": "75inchtv", "75inchtv16.jpg": "75inchtv", "massivetv195.jpg": "massivetv", "hugetv203.jpg": "hugetv", "massivetv127.jpg": "massivetv", "hugetv148.jpg": "hugetv", "hugetv181.jpg": "hugetv", "85inchtv53.jpg": "85inchtv", "gianttv44.jpg": "gianttv", "75inchtv176.jpg": "75inchtv", "hugetv171.jpg": "hugetv", "hugetv127.jpg": "hugetv", "massivetv164.jpg": "massivetv", "hugetv187.jpg": "hugetv", "85inchtv50.jpg": "85inchtv", "massivetv141.jpg": "massivetv", "gianttv87.jpg": "gianttv", "massivetv4.jpg": "massivetv", "massivetv231.jpg": "massivetv", "gianttv129.jpg": "gianttv", "gianttv85.jpg": "gianttv", "massivetv25.jpg": "massivetv", "massivetv52.jpg": "massivetv", "hugetv146.jpg": "hugetv", "hugetv157.jpg": "hugetv", "massivetv150.jpg": "massivetv", "75inchtv26.jpg": "75inchtv", "hugetv120.jpg": "hugetv", "hugetv223.jpg": "hugetv", "gianttv143.jpg": "gianttv", "hugetv41.jpg": "hugetv", "massivetv161.jpg": "massivetv", "75inchtv106.jpg": "75inchtv", "massivetv124.jpg": "massivetv", "75inchtv75.jpg": "75inchtv", "hugetv217.jpg": "hugetv", "hugetv201.jpg": "hugetv", "75inchtv116.jpg": "75inchtv", "hugetv183.jpg": "hugetv", "massivetv18.jpg": "massivetv", "75inchtv178.jpg": "75inchtv", "massivetv242.jpg": "massivetv", "gianttv192.jpg": "gianttv", "gianttv148.jpg": "gianttv", "hugetv260.jpg": "hugetv", "massivetv143.jpg": "massivetv", "hugetv0.jpg": "hugetv", "hugetv98.jpg": "hugetv", "75inchtv246.jpg": "75inchtv", "75inchtv183.jpg": "75inchtv", "massivetv206.jpg": "massivetv", "hugetv77.jpg": "hugetv", "75inchtv165.jpg": "75inchtv", "85inchtv31.jpg": "85inchtv", "hugetv206.jpg": "hugetv", "hugetv45.jpg": "hugetv", "75inchtv63.jpg": "75inchtv", "85inchtv35.jpg": "85inchtv", "hugetv233.jpg": "hugetv", "hugetv122.jpg": "hugetv", "75inchtv260.jpg": "75inchtv", "massivetv191.jpg": "massivetv", "gianttv71.jpg": "gianttv", "hugetv210.jpg": "hugetv", "75inchtv219.jpg": "75inchtv", "massivetv185.jpg": "massivetv", "hugetv113.jpg": "hugetv", "75inchtv118.jpg": "75inchtv", "massivetv21.jpg": "massivetv", "85inchtv26.jpg": "85inchtv", "gianttv237.jpg": "gianttv", "75inchtv245.jpg": "75inchtv", "hugetv62.jpg": "hugetv", "85inchtv11.jpg": "85inchtv", "gianttv136.jpg": "gianttv", "massivetv153.jpg": "massivetv", "75inchtv201.jpg": "75inchtv", "gianttv151.jpg": "gianttv", "gianttv235.jpg": "gianttv", "gianttv81.jpg": "gianttv", "hugetv134.jpg": "hugetv", "hugetv218.jpg": "hugetv", "gianttv213.jpg": "gianttv", "85inchtv44.jpg": "85inchtv", "hugetv16.jpg": "hugetv", "massivetv98.jpg": "massivetv", "massivetv86.jpg": "massivetv", "hugetv20.jpg": "hugetv", "75inchtv5.jpg": "75inchtv", "hugetv151.jpg": "hugetv", "75inchtv19.jpg": "75inchtv", "massivetv83.jpg": "massivetv", "75inchtv147.jpg": "75inchtv", "gianttv31.jpg": "gianttv", "gianttv94.jpg": "gianttv", "massivetv9.jpg": "massivetv", "massivetv156.jpg": "massivetv", "massivetv204.jpg": "massivetv", "massivetv208.jpg": "massivetv", "gianttv20.jpg": "gianttv", "massivetv53.jpg": "massivetv", "gianttv236.jpg": "gianttv", "75inchtv235.jpg": "75inchtv", "75inchtv241.jpg": "75inchtv", "75inchtv88.jpg": "75inchtv", "gianttv16.jpg": "gianttv", "75inchtv166.jpg": "75inchtv", "gianttv22.jpg": "gianttv", "hugetv100.jpg": "hugetv", "massivetv16.jpg": "massivetv", "massivetv8.jpg": "massivetv", "75inchtv50.jpg": "75inchtv", "hugetv193.jpg": "hugetv", "gianttv242.jpg": "gianttv", "75inchtv238.jpg": "75inchtv", "gianttv158.jpg": "gianttv", "gianttv59.jpg": "gianttv", "hugetv143.jpg": "hugetv", "75inchtv194.jpg": "75inchtv", "75inchtv253.jpg": "75inchtv", "massivetv62.jpg": "massivetv", "gianttv24.jpg": "gianttv", "75inchtv164.jpg": "75inchtv", "gianttv234.jpg": "gianttv", "75inchtv112.jpg": "75inchtv", "gianttv229.jpg": "gianttv", "massivetv44.jpg": "massivetv", "gianttv122.jpg": "gianttv", "gianttv241.jpg": "gianttv", "85inchtv79.jpg": "85inchtv", "massivetv230.jpg": "massivetv", "75inchtv222.jpg": "75inchtv", "75inchtv185.jpg": "75inchtv", "75inchtv188.jpg": "75inchtv", "75inchtv174.jpg": "75inchtv", "75inchtv162.jpg": "75inchtv", "massivetv155.jpg": "massivetv", "massivetv80.jpg": "massivetv", "gianttv47.jpg": "gianttv", "massivetv232.jpg": "massivetv", "gianttv180.jpg": "gianttv", "75inchtv51.jpg": "75inchtv", "gianttv21.jpg": "gianttv", "massivetv205.jpg": "massivetv", "hugetv124.jpg": "hugetv", "75inchtv123.jpg": "75inchtv", "gianttv133.jpg": "gianttv", "hugetv94.jpg": "hugetv", "hugetv30.jpg": "hugetv", "hugetv153.jpg": "hugetv", "75inchtv9.jpg": "75inchtv", "75inchtv181.jpg": "75inchtv", "massivetv193.jpg": "massivetv", "85inchtv30.jpg": "85inchtv", "massivetv2.jpg": "massivetv", "hugetv14.jpg": "hugetv", "gianttv174.jpg": "gianttv", "massivetv94.jpg": "massivetv", "massivetv171.jpg": "massivetv", "hugetv101.jpg": "hugetv", "hugetv7.jpg": "hugetv", "75inchtv41.jpg": "75inchtv", "hugetv138.jpg": "hugetv", "massivetv163.jpg": "massivetv", "hugetv3.jpg": "hugetv", "gianttv12.jpg": "gianttv", "hugetv52.jpg": "hugetv", "85inchtv16.jpg": "85inchtv", "85inchtv66.jpg": "85inchtv", "75inchtv236.jpg": "75inchtv", "75inchtv1.jpg": "75inchtv", "gianttv160.jpg": "gianttv", "hugetv78.jpg": "hugetv", "gianttv124.jpg": "gianttv", "85inchtv68.jpg": "85inchtv", "75inchtv129.jpg": "75inchtv", "75inchtv232.jpg": "75inchtv", "gianttv78.jpg": "gianttv", "gianttv123.jpg": "gianttv", "hugetv231.jpg": "hugetv", "gianttv231.jpg": "gianttv", "hugetv69.jpg": "hugetv", "gianttv220.jpg": "gianttv", "85inchtv36.jpg": "85inchtv", "85inchtv37.jpg": "85inchtv", "gianttv156.jpg": "gianttv", "massivetv118.jpg": "massivetv", "massivetv235.jpg": "massivetv", "massivetv139.jpg": "massivetv", "85inchtv40.jpg": "85inchtv", "massivetv178.jpg": "massivetv", "75inchtv215.jpg": "75inchtv", "hugetv99.jpg": "hugetv", "75inchtv113.jpg": "75inchtv", "gianttv254.jpg": "gianttv", "gianttv134.jpg": "gianttv", "75inchtv257.jpg": "75inchtv", "massivetv179.jpg": "massivetv", "hugetv4.jpg": "hugetv", "hugetv169.jpg": "hugetv", "85inchtv45.jpg": "85inchtv", "75inchtv59.jpg": "75inchtv", "75inchtv89.jpg": "75inchtv", "75inchtv233.jpg": "75inchtv", "massivetv20.jpg": "massivetv", "gianttv41.jpg": "gianttv", "massivetv49.jpg": "massivetv", "hugetv43.jpg": "hugetv", "75inchtv252.jpg": "75inchtv", "85inchtv3.jpg": "85inchtv", "gianttv181.jpg": "gianttv", "massivetv200.jpg": "massivetv", "hugetv49.jpg": "hugetv", "massivetv90.jpg": "massivetv", "gianttv10.jpg": "gianttv", "gianttv70.jpg": "gianttv", "massivetv102.jpg": "massivetv", "gianttv175.jpg": "gianttv", "75inchtv143.jpg": "75inchtv", "gianttv36.jpg": "gianttv", "massivetv233.jpg": "massivetv", "75inchtv84.jpg": "75inchtv", "gianttv30.jpg": "gianttv", "75inchtv13.jpg": "75inchtv", "hugetv185.jpg": "hugetv", "hugetv192.jpg": "hugetv", "75inchtv61.jpg": "75inchtv", "hugetv97.jpg": "hugetv", "hugetv26.jpg": "hugetv", "gianttv186.jpg": "gianttv", "hugetv106.jpg": "hugetv", "massivetv240.jpg": "massivetv", "75inchtv36.jpg": "75inchtv", "75inchtv99.jpg": "75inchtv", "75inchtv177.jpg": "75inchtv", "massivetv57.jpg": "massivetv", "75inchtv67.jpg": "75inchtv", "massivetv210.jpg": "massivetv", "hugetv53.jpg": "hugetv", "massivetv45.jpg": "massivetv", "75inchtv8.jpg": "75inchtv", "massivetv218.jpg": "massivetv", "gianttv145.jpg": "gianttv", "hugetv102.jpg": "hugetv", "gianttv108.jpg": "gianttv", "75inchtv218.jpg": "75inchtv", "75inchtv234.jpg": "75inchtv", "gianttv219.jpg": "gianttv", "hugetv125.jpg": "hugetv", "gianttv252.jpg": "gianttv", "hugetv160.jpg": "hugetv", "85inchtv0.jpg": "85inchtv", "massivetv54.jpg": "massivetv", "hugetv232.jpg": "hugetv", "massivetv238.jpg": "massivetv", "75inchtv105.jpg": "75inchtv", "massivetv81.jpg": "massivetv", "gianttv211.jpg": "gianttv", "hugetv188.jpg": "hugetv", "massivetv63.jpg": "massivetv", "75inchtv153.jpg": "75inchtv", "85inchtv69.jpg": "85inchtv", "hugetv245.jpg": "hugetv", "75inchtv256.jpg": "75inchtv", "massivetv202.jpg": "massivetv", "hugetv132.jpg": "hugetv", "gianttv114.jpg": "gianttv", "75inchtv128.jpg": "75inchtv", "75inchtv228.jpg": "75inchtv", "gianttv146.jpg": "gianttv", "85inchtv33.jpg": "85inchtv", "85inchtv76.jpg": "85inchtv", "85inchtv29.jpg": "85inchtv", "gianttv17.jpg": "gianttv", "85inchtv10.jpg": "85inchtv", "gianttv99.jpg": "gianttv", "75inchtv186.jpg": "75inchtv", "massivetv181.jpg": "massivetv", "hugetv147.jpg": "hugetv", "massivetv106.jpg": "massivetv", "gianttv168.jpg": "gianttv", "hugetv63.jpg": "hugetv", "massivetv43.jpg": "massivetv", "75inchtv144.jpg": "75inchtv", "hugetv139.jpg": "hugetv", "gianttv132.jpg": "gianttv", "massivetv125.jpg": "massivetv", "75inchtv25.jpg": "75inchtv", "massivetv65.jpg": "massivetv", "75inchtv32.jpg": "75inchtv", "massivetv36.jpg": "massivetv", "75inchtv198.jpg": "75inchtv", "hugetv96.jpg": "hugetv", "massivetv177.jpg": "massivetv", "hugetv142.jpg": "hugetv", "75inchtv109.jpg": "75inchtv", "massivetv142.jpg": "massivetv", "hugetv253.jpg": "hugetv", "hugetv164.jpg": "hugetv", "hugetv111.jpg": "hugetv", "massivetv93.jpg": "massivetv", "85inchtv67.jpg": "85inchtv", "75inchtv22.jpg": "75inchtv", "75inchtv200.jpg": "75inchtv", "hugetv235.jpg": "hugetv", "massivetv190.jpg": "massivetv", "gianttv38.jpg": "gianttv", "gianttv95.jpg": "gianttv", "hugetv29.jpg": "hugetv", "gianttv13.jpg": "gianttv", "75inchtv226.jpg": "75inchtv", "hugetv189.jpg": "hugetv", "hugetv133.jpg": "hugetv", "75inchtv90.jpg": "75inchtv", "massivetv180.jpg": "massivetv", "hugetv65.jpg": "hugetv", "75inchtv40.jpg": "75inchtv", "85inchtv61.jpg": "85inchtv", "hugetv38.jpg": "hugetv", "gianttv131.jpg": "gianttv", "75inchtv0.jpg": "75inchtv", "massivetv225.jpg": "massivetv", "gianttv159.jpg": "gianttv", "gianttv46.jpg": "gianttv", "hugetv250.jpg": "hugetv", "gianttv216.jpg": "gianttv", "85inchtv70.jpg": "85inchtv", "gianttv3.jpg": "gianttv", "gianttv161.jpg": "gianttv", "massivetv188.jpg": "massivetv", "gianttv196.jpg": "gianttv", "75inchtv72.jpg": "75inchtv", "massivetv121.jpg": "massivetv", "gianttv84.jpg": "gianttv", "hugetv240.jpg": "hugetv", "massivetv72.jpg": "massivetv", "75inchtv77.jpg": "75inchtv", "hugetv221.jpg": "hugetv", "gianttv79.jpg": "gianttv", "85inchtv4.jpg": "85inchtv", "hugetv44.jpg": "hugetv", "hugetv252.jpg": "hugetv", "75inchtv192.jpg": "75inchtv", "75inchtv127.jpg": "75inchtv", "gianttv32.jpg": "gianttv", "massivetv56.jpg": "massivetv", "hugetv172.jpg": "hugetv", "hugetv66.jpg": "hugetv", "hugetv6.jpg": "hugetv", "75inchtv43.jpg": "75inchtv", "massivetv82.jpg": "massivetv", "75inchtv6.jpg": "75inchtv", "gianttv215.jpg": "gianttv", "gianttv15.jpg": "gianttv", "85inchtv71.jpg": "85inchtv", "75inchtv159.jpg": "75inchtv", "hugetv22.jpg": "hugetv", "gianttv9.jpg": "gianttv", "85inchtv32.jpg": "85inchtv", "gianttv52.jpg": "gianttv", "gianttv66.jpg": "gianttv", "hugetv92.jpg": "hugetv", "massivetv254.jpg": "massivetv", "75inchtv74.jpg": "75inchtv", "gianttv201.jpg": "gianttv", "hugetv1.jpg": "hugetv", "75inchtv76.jpg": "75inchtv", "gianttv40.jpg": "gianttv", "75inchtv27.jpg": "75inchtv", "hugetv12.jpg": "hugetv", "85inchtv78.jpg": "85inchtv", "hugetv179.jpg": "hugetv", "massivetv247.jpg": "massivetv", "hugetv114.jpg": "hugetv", "gianttv184.jpg": "gianttv", "massivetv10.jpg": "massivetv", "massivetv30.jpg": "massivetv", "gianttv64.jpg": "gianttv", "hugetv40.jpg": "hugetv", "85inchtv64.jpg": "85inchtv", "massivetv207.jpg": "massivetv", "75inchtv199.jpg": "75inchtv", "massivetv6.jpg": "massivetv", "75inchtv163.jpg": "75inchtv", "75inchtv71.jpg": "75inchtv", "massivetv131.jpg": "massivetv", "hugetv214.jpg": "hugetv", "hugetv60.jpg": "hugetv", "gianttv199.jpg": "gianttv", "gianttv53.jpg": "gianttv", "75inchtv173.jpg": "75inchtv", "hugetv108.jpg": "hugetv", "75inchtv150.jpg": "75inchtv", "75inchtv193.jpg": "75inchtv", "75inchtv230.jpg": "75inchtv", "hugetv39.jpg": "hugetv", "hugetv88.jpg": "hugetv", "massivetv120.jpg": "massivetv", "massivetv203.jpg": "massivetv", "hugetv246.jpg": "hugetv", "gianttv197.jpg": "gianttv", "gianttv11.jpg": "gianttv", "hugetv249.jpg": "hugetv", "massivetv117.jpg": "massivetv", "75inchtv56.jpg": "75inchtv", "75inchtv140.jpg": "75inchtv", "massivetv55.jpg": "massivetv", "massivetv73.jpg": "massivetv", "gianttv56.jpg": "gianttv", "75inchtv225.jpg": "75inchtv", "hugetv48.jpg": "hugetv", "hugetv200.jpg": "hugetv", "75inchtv155.jpg": "75inchtv", "gianttv58.jpg": "gianttv", "75inchtv7.jpg": "75inchtv", "gianttv34.jpg": "gianttv", "massivetv226.jpg": "massivetv", "75inchtv33.jpg": "75inchtv", "hugetv74.jpg": "hugetv", "75inchtv203.jpg": "75inchtv", "75inchtv73.jpg": "75inchtv", "85inchtv51.jpg": "85inchtv", "85inchtv42.jpg": "85inchtv", "gianttv0.jpg": "gianttv", "gianttv18.jpg": "gianttv", "gianttv26.jpg": "gianttv", "hugetv59.jpg": "hugetv", "gianttv208.jpg": "gianttv", "massivetv11.jpg": "massivetv", "gianttv142.jpg": "gianttv", "hugetv176.jpg": "hugetv", "75inchtv28.jpg": "75inchtv", "gianttv83.jpg": "gianttv", "hugetv104.jpg": "hugetv", "hugetv81.jpg": "hugetv", "75inchtv151.jpg": "75inchtv", "hugetv131.jpg": "hugetv", "massivetv257.jpg": "massivetv", "gianttv137.jpg": "gianttv", "85inchtv25.jpg": "85inchtv", "hugetv222.jpg": "hugetv", "hugetv256.jpg": "hugetv", "hugetv50.jpg": "hugetv", "massivetv134.jpg": "massivetv", "85inchtv7.jpg": "85inchtv", "massivetv194.jpg": "massivetv", "hugetv202.jpg": "hugetv", "hugetv35.jpg": "hugetv", "massivetv173.jpg": "massivetv", "hugetv166.jpg": "hugetv", "75inchtv227.jpg": "75inchtv", "75inchtv146.jpg": "75inchtv", "hugetv9.jpg": "hugetv", "75inchtv205.jpg": "75inchtv", "hugetv254.jpg": "hugetv", "massivetv166.jpg": "massivetv", "75inchtv24.jpg": "75inchtv", "75inchtv207.jpg": "75inchtv", "hugetv224.jpg": "hugetv", "75inchtv18.jpg": "75inchtv", "85inchtv12.jpg": "85inchtv", "hugetv149.jpg": "hugetv", "massivetv174.jpg": "massivetv", "massivetv209.jpg": "massivetv", "75inchtv20.jpg": "75inchtv", "gianttv157.jpg": "gianttv", "75inchtv223.jpg": "75inchtv", "75inchtv121.jpg": "75inchtv", "gianttv221.jpg": "gianttv", "massivetv19.jpg": "massivetv", "massivetv24.jpg": "massivetv", "massivetv151.jpg": "massivetv", "hugetv182.jpg": "hugetv", "75inchtv46.jpg": "75inchtv", "massivetv64.jpg": "massivetv", "hugetv61.jpg": "hugetv", "hugetv72.jpg": "hugetv", "85inchtv60.jpg": "85inchtv", "gianttv45.jpg": "gianttv", "gianttv200.jpg": "gianttv", "massivetv123.jpg": "massivetv", "75inchtv54.jpg": "75inchtv", "massivetv228.jpg": "massivetv", "75inchtv2.jpg": "75inchtv", "85inchtv18.jpg": "85inchtv", "75inchtv240.jpg": "75inchtv", "massivetv67.jpg": "massivetv", "massivetv246.jpg": "massivetv", "massivetv229.jpg": "massivetv", "hugetv205.jpg": "hugetv", "gianttv149.jpg": "gianttv", "85inchtv6.jpg": "85inchtv", "75inchtv102.jpg": "75inchtv", "85inchtv8.jpg": "85inchtv", "hugetv105.jpg": "hugetv", "75inchtv189.jpg": "75inchtv", "gianttv130.jpg": "gianttv", "gianttv7.jpg": "gianttv", "75inchtv191.jpg": "75inchtv", "massivetv85.jpg": "massivetv", "hugetv64.jpg": "hugetv", "massivetv108.jpg": "massivetv", "gianttv119.jpg": "gianttv", "gianttv243.jpg": "gianttv", "hugetv168.jpg": "hugetv", "hugetv58.jpg": "hugetv", "75inchtv213.jpg": "75inchtv", "hugetv144.jpg": "hugetv", "gianttv1.jpg": "gianttv", "hugetv184.jpg": "hugetv", "massivetv107.jpg": "massivetv", "massivetv199.jpg": "massivetv", "75inchtv135.jpg": "75inchtv", "75inchtv158.jpg": "75inchtv", "hugetv213.jpg": "hugetv", "75inchtv130.jpg": "75inchtv", "85inchtv48.jpg": "85inchtv", "85inchtv63.jpg": "85inchtv", "gianttv228.jpg": "gianttv", "hugetv110.jpg": "hugetv", "gianttv165.jpg": "gianttv", "75inchtv229.jpg": "75inchtv", "hugetv129.jpg": "hugetv", "gianttv126.jpg": "gianttv", "75inchtv64.jpg": "75inchtv", "hugetv204.jpg": "hugetv", "gianttv135.jpg": "gianttv", "gianttv67.jpg": "gianttv", "75inchtv169.jpg": "75inchtv", "hugetv112.jpg": "hugetv", "75inchtv167.jpg": "75inchtv", "hugetv87.jpg": "hugetv", "massivetv216.jpg": "massivetv", "massivetv196.jpg": "massivetv", "massivetv96.jpg": "massivetv", "massivetv113.jpg": "massivetv", "hugetv68.jpg": "hugetv", "75inchtv137.jpg": "75inchtv", "gianttv238.jpg": "gianttv", "gianttv91.jpg": "gianttv", "massivetv189.jpg": "massivetv", "hugetv199.jpg": "hugetv", "gianttv154.jpg": "gianttv", "75inchtv4.jpg": "75inchtv", "85inchtv1.jpg": "85inchtv", "gianttv210.jpg": "gianttv", "gianttv202.jpg": "gianttv", "gianttv106.jpg": "gianttv", "massivetv34.jpg": "massivetv", "gianttv89.jpg": "gianttv", "75inchtv247.jpg": "75inchtv", "gianttv98.jpg": "gianttv", "gianttv178.jpg": "gianttv", "gianttv240.jpg": "gianttv", "75inchtv104.jpg": "75inchtv", "massivetv255.jpg": "massivetv", "gianttv77.jpg": "gianttv", "75inchtv156.jpg": "75inchtv", "gianttv176.jpg": "gianttv", "75inchtv87.jpg": "75inchtv", "gianttv198.jpg": "gianttv", "gianttv147.jpg": "gianttv", "massivetv100.jpg": "massivetv", "massivetv40.jpg": "massivetv", "75inchtv138.jpg": "75inchtv", "massivetv223.jpg": "massivetv", "gianttv167.jpg": "gianttv", "gianttv226.jpg": "gianttv", "massivetv126.jpg": "massivetv", "75inchtv220.jpg": "75inchtv", "massivetv48.jpg": "massivetv", "massivetv66.jpg": "massivetv", "gianttv48.jpg": "gianttv", "hugetv158.jpg": "hugetv", "hugetv24.jpg": "hugetv", "85inchtv80.jpg": "85inchtv", "75inchtv86.jpg": "75inchtv", "75inchtv82.jpg": "75inchtv", "85inchtv2.jpg": "85inchtv", "gianttv65.jpg": "gianttv", "massivetv147.jpg": "massivetv", "hugetv2.jpg": "hugetv", "75inchtv254.jpg": "75inchtv", "massivetv47.jpg": "massivetv", "75inchtv172.jpg": "75inchtv", "hugetv73.jpg": "hugetv", "gianttv74.jpg": "gianttv", "85inchtv52.jpg": "85inchtv", "75inchtv202.jpg": "75inchtv", "gianttv69.jpg": "gianttv", "gianttv163.jpg": "gianttv", "gianttv6.jpg": "gianttv", "75inchtv131.jpg": "75inchtv", "gianttv23.jpg": "gianttv", "massivetv101.jpg": "massivetv", "gianttv19.jpg": "gianttv", "hugetv170.jpg": "hugetv", "85inchtv17.jpg": "85inchtv", "75inchtv92.jpg": "75inchtv", "gianttv248.jpg": "gianttv", "hugetv89.jpg": "hugetv", "75inchtv108.jpg": "75inchtv", "gianttv42.jpg": "gianttv", "hugetv13.jpg": "hugetv", "gianttv113.jpg": "gianttv", "massivetv89.jpg": "massivetv", "hugetv121.jpg": "hugetv", "hugetv175.jpg": "hugetv", "gianttv93.jpg": "gianttv", "massivetv168.jpg": "massivetv", "massivetv237.jpg": "massivetv", "75inchtv171.jpg": "75inchtv", "hugetv211.jpg": "hugetv", "massivetv28.jpg": "massivetv", "gianttv14.jpg": "gianttv", "hugetv25.jpg": "hugetv", "gianttv225.jpg": "gianttv", "hugetv130.jpg": "hugetv", "gianttv152.jpg": "gianttv", "massivetv75.jpg": "massivetv", "massivetv140.jpg": "massivetv", "gianttv109.jpg": "gianttv", "gianttv247.jpg": "gianttv", "hugetv11.jpg": "hugetv", "75inchtv179.jpg": "75inchtv", "85inchtv13.jpg": "85inchtv", "hugetv57.jpg": "hugetv", "75inchtv23.jpg": "75inchtv", "75inchtv65.jpg": "75inchtv", "hugetv10.jpg": "hugetv", "hugetv195.jpg": "hugetv", "massivetv39.jpg": "massivetv", "gianttv51.jpg": "gianttv", "75inchtv187.jpg": "75inchtv", "massivetv234.jpg": "massivetv", "85inchtv14.jpg": "85inchtv", "hugetv126.jpg": "hugetv", "massivetv87.jpg": "massivetv", "hugetv145.jpg": "hugetv", "75inchtv69.jpg": "75inchtv", "hugetv47.jpg": "hugetv", "75inchtv209.jpg": "75inchtv", "hugetv54.jpg": "hugetv", "75inchtv49.jpg": "75inchtv", "gianttv193.jpg": "gianttv", "hugetv162.jpg": "hugetv", "gianttv170.jpg": "gianttv", "hugetv84.jpg": "hugetv", "gianttv39.jpg": "gianttv", "hugetv93.jpg": "hugetv", "75inchtv29.jpg": "75inchtv", "massivetv22.jpg": "massivetv", "massivetv224.jpg": "massivetv", "75inchtv95.jpg": "75inchtv", "75inchtv152.jpg": "75inchtv", "85inchtv23.jpg": "85inchtv", "hugetv80.jpg": "hugetv", "hugetv27.jpg": "hugetv", "massivetv99.jpg": "massivetv", "85inchtv73.jpg": "85inchtv", "gianttv29.jpg": "gianttv", "massivetv32.jpg": "massivetv", "gianttv141.jpg": "gianttv", "massivetv110.jpg": "massivetv", "hugetv37.jpg": "hugetv", "75inchtv57.jpg": "75inchtv", "massivetv51.jpg": "massivetv", "massivetv176.jpg": "massivetv", "75inchtv211.jpg": "75inchtv", "gianttv127.jpg": "gianttv", "hugetv207.jpg": "hugetv", "massivetv248.jpg": "massivetv", "hugetv31.jpg": "hugetv", "gianttv50.jpg": "gianttv", "massivetv95.jpg": "massivetv", "gianttv72.jpg": "gianttv", "massivetv50.jpg": "massivetv", "gianttv205.jpg": "gianttv", "hugetv177.jpg": "hugetv", "75inchtv79.jpg": "75inchtv", "75inchtv60.jpg": "75inchtv", "massivetv88.jpg": "massivetv", "massivetv222.jpg": "massivetv", "gianttv121.jpg": "gianttv", "gianttv27.jpg": "gianttv", "hugetv248.jpg": "hugetv", "gianttv68.jpg": "gianttv", "75inchtv206.jpg": "75inchtv", "gianttv35.jpg": "gianttv", "hugetv161.jpg": "hugetv", "75inchtv55.jpg": "75inchtv", "gianttv249.jpg": "gianttv", "gianttv179.jpg": "gianttv", "75inchtv37.jpg": "75inchtv", "75inchtv91.jpg": "75inchtv", "hugetv180.jpg": "hugetv", "hugetv216.jpg": "hugetv", "gianttv43.jpg": "gianttv", "massivetv61.jpg": "massivetv", "gianttv171.jpg": "gianttv", "massivetv42.jpg": "massivetv", "75inchtv17.jpg": "75inchtv", "gianttv138.jpg": "gianttv", "75inchtv81.jpg": "75inchtv", "75inchtv45.jpg": "75inchtv", "hugetv128.jpg": "hugetv", "gianttv101.jpg": "gianttv", "75inchtv83.jpg": "75inchtv", "gianttv28.jpg": "gianttv", "75inchtv214.jpg": "75inchtv", "85inchtv46.jpg": "85inchtv"}